LICENSE
MANIFEST.in
README.md
demo.gif
setup.py
docs/.nojekyll
docs/Makefile
docs/converteol.log
docs/index.html
docs/make.bat
docs/build/doctrees/api.doctree
docs/build/doctrees/environment.pickle
docs/build/doctrees/index.doctree
docs/build/doctrees/intro.doctree
docs/build/doctrees/modules.doctree
docs/build/html/.buildinfo
docs/build/html/api.html
docs/build/html/genindex.html
docs/build/html/index.html
docs/build/html/intro.html
docs/build/html/modules.html
docs/build/html/objects.inv
docs/build/html/py-modindex.html
docs/build/html/pyqtlineeditprogressbar.html
docs/build/html/search.html
docs/build/html/searchindex.js
docs/build/html/_images/behaviors.gif
docs/build/html/_images/builtin_color_table.png
docs/build/html/_images/logo.gif
docs/build/html/_modules/index.html
docs/build/html/_modules/pyqtlineeditprogressbar.html
docs/build/html/_modules/pyqtlineeditprogressbar/__init__.html
docs/build/html/_sources/api.rst.txt
docs/build/html/_sources/index.rst.txt
docs/build/html/_sources/intro.rst.txt
docs/build/html/_sources/modules.rst.txt
docs/build/html/_sources/pyqtlineeditprogressbar.rst.txt
docs/build/html/_static/alabaster.css
docs/build/html/_static/basic.css
docs/build/html/_static/behaviors.gif
docs/build/html/_static/behaviors.py
docs/build/html/_static/builtin_color_table.pdn
docs/build/html/_static/builtin_color_table.png
docs/build/html/_static/custom.css
docs/build/html/_static/doctools.js
docs/build/html/_static/documentation_options.js
docs/build/html/_static/file.png
docs/build/html/_static/jquery-3.5.1.js
docs/build/html/_static/jquery.js
docs/build/html/_static/language_data.js
docs/build/html/_static/logo.gif
docs/build/html/_static/logo.py
docs/build/html/_static/minus.png
docs/build/html/_static/plus.png
docs/build/html/_static/pygments.css
docs/build/html/_static/searchtools.js
docs/build/html/_static/underscore-1.3.1.js
docs/build/html/_static/underscore.js
docs/build/html/_static/css/badge_only.css
docs/build/html/_static/css/theme.css
pyqtlineeditprogressbar.egg-info/PKG-INFO
pyqtlineeditprogressbar.egg-info/SOURCES.txt
pyqtlineeditprogressbar.egg-info/dependency_links.txt
pyqtlineeditprogressbar.egg-info/requires.txt
pyqtlineeditprogressbar.egg-info/top_level.txt