Metadata-Version: 2.1
Name: pyqtlineeditprogressbar
Version: 0.3.5
Summary: A custom PyQt widget that places a configurable progress bar in the background of a QLineEdit widget.
Home-page: http://github.com/eruber/pyqtlineeditprogressbar
Author: E.R. Uber
Author-email: eruber@gmail.com
License: GPLv3
Download-URL: https://github.com/eruber/PyQtLineEditProgressBar/archive/v0.3.0.tar.gz
Platform: UNKNOWN
Classifier: Development Status :: 4 - Beta
Classifier: Intended Audience :: Developers
Classifier: License :: OSI Approved :: GNU General Public License v3 (GPLv3)
Classifier: Programming Language :: Python :: 3.7
Classifier: Programming Language :: Python :: 3.8
